dockposegen.py
dockposegen-1.0.0.dist-info/METADATA
dockposegen-1.0.0.dist-info/WHEEL
dockposegen-1.0.0.dist-info/entry_points.txt
dockposegen-1.0.0.dist-info/top_level.txt
dockposegen-1.0.0.dist-info/RECORD
