Metadata-Version: 2.4
Name: dockposegen
Version: 1.0.0
Summary: A Tool for Ligands pose extraction and Complex Building Workflow
Home-page: https://github.com/alpha-horizon/dockposegen.git
Author: fred
Classifier: Programming Language :: Python :: 3
Classifier: License :: OSI Approved :: MIT License
Classifier: Operating System :: OS Independent
Requires-Dist: numpy
Requires-Dist: pandas
Dynamic: author
Dynamic: classifier
Dynamic: description
Dynamic: description-content-type
Dynamic: home-page
Dynamic: requires-dist
Dynamic: summary
